transmission_client/__init__.py
transmission_client/__main__.py
transmission_client/fastapi_server.py
transmission_client/mcp_server.py
transmission_client/wrapper/__init__.py
transmission_client/wrapper/client.py
transmission_mcp-1.0.1.dist-info/METADATA
transmission_mcp-1.0.1.dist-info/WHEEL
transmission_mcp-1.0.1.dist-info/entry_points.txt
transmission_mcp-1.0.1.dist-info/licenses/LICENSE
transmission_mcp-1.0.1.dist-info/RECORD
