Metadata-Version: 2.4
Name: transmission-mcp
Version: 1.0.1
Summary: Python wrapper & MCP server for the Transmission API
Project-URL: Repository, https://github.com/philogicae/transmission-mcp
Project-URL: Release, https://github.com/philogicae/transmission-mcp/releases
Project-URL: DeepWiki, https://deepwiki.com/philogicae/transmission-mcp
Author: philogicae
License-File: LICENSE
Classifier: License :: OSI Approved :: MIT License
Classifier: Operating System :: OS Independent
Classifier: Programming Language :: Python :: 3
Requires-Python: <4.0,>=3.10
Requires-Dist: fastapi
Requires-Dist: fastmcp
Requires-Dist: python-dotenv
Requires-Dist: transmission-rpc==7.0.11
Requires-Dist: uvicorn
